culturecoded/__init__.py
culturecoded/client.py
culturecoded/types.py
culturecoded-1.0.1.dist-info/METADATA
culturecoded-1.0.1.dist-info/WHEEL
culturecoded-1.0.1.dist-info/top_level.txt
culturecoded-1.0.1.dist-info/RECORD
