Metadata-Version: 2.4
Name: culturecoded
Version: 1.0.1
Summary: Official Python SDK for CultureCoded - Cultural UX Intelligence Platform
Author-email: CultureCoded <hello@culturecoded.io>
License: MIT
Project-URL: Homepage, https://culturecoded.io
Project-URL: Documentation, https://culturecoded.io/api-docs
Project-URL: Repository, https://github.com/culturecoded/sdk-python
Project-URL: Issues, https://github.com/culturecoded/sdk-python/issues
Keywords: culturecoded,cultural-ux,design,localization,figma,sdk
Classifier: Development Status :: 4 - Beta
Classifier: Intended Audience :: Developers
Classifier: License :: OSI Approved :: MIT License
Classifier: Operating System :: OS Independent
Classifier: Programming Language :: Python :: 3
Classifier: Programming Language :: Python :: 3.8
Classifier: Programming Language :: Python :: 3.9
Classifier: Programming Language :: Python :: 3.10
Classifier: Programming Language :: Python :: 3.11
Classifier: Programming Language :: Python :: 3.12
Classifier: Topic :: Software Development :: Libraries :: Python Modules
Requires-Python: >=3.8
Requires-Dist: requests>=2.25.0
Provides-Extra: dev
Requires-Dist: pytest>=7.0.0; extra == "dev"
Requires-Dist: pytest-cov>=4.0.0; extra == "dev"
Requires-Dist: black>=23.0.0; extra == "dev"
Requires-Dist: mypy>=1.0.0; extra == "dev"
Requires-Dist: types-requests>=2.28.0; extra == "dev"
